TopologyValidator/TopologyValidator.py
TopologyValidator/__init__.py
TopologyValidator-1.0.0.dist-info/METADATA
TopologyValidator-1.0.0.dist-info/WHEEL
TopologyValidator-1.0.0.dist-info/top_level.txt
TopologyValidator-1.0.0.dist-info/RECORD
