Metadata-Version: 2.1
Name: TopologyValidator
Version: 1.0.0
Summary: Validates the converted topology against the given OpenAPI specifications
Author: Sai Krishna Voruganti
Author-email: saikrishnavoruganti@gmail.com
Requires-Dist: pyyaml
Requires-Dist: jsonref
Requires-Dist: jsonschema
